{
  "school": {
    "schoolCode": "10049",
    "schoolName": "中国戏曲学院",
    "schoolTotalPlan": null,
    "schoolLocation": "北京市",
    "consultPhone": "010-63339858",
    "programCount": 17
  },
  "programs": [
    {
      "batchName": "本科提前批艺术类本科第一批",
      "schoolCode": "10049",
      "schoolName": "中国戏曲学院",
      "schoolTotalPlan": null,
      "schoolLocation": "北京市",
      "consultPhone": "010-63339858",
      "majorGroupCode": "201",
      "majorGroupPlan": null,
      "firstSubject": null,
      "secondSubject": null,
      "majorCode": "001",
      "majorName": "作曲与作曲技术理论",
      "planCount": "不编制分省计划",
      "durationYears": 5,
      "tuitionPerYear": "免费",
      "campus": null,
      "remarks": "戏曲作曲福建莆仙戏 艺术校考类,5年,免费",
      "pdfPage": 51,
      "bookPage": 3
    },
    {
      "batchName": "本科提前批艺术类本科第一批",
      "schoolCode": "10049",
      "schoolName": "中国戏曲学院",
      "schoolTotalPlan": null,
      "schoolLocation": "北京市",
      "consultPhone": "010-63339858",
      "majorGroupCode": "201",
      "majorGroupPlan": null,
      "firstSubject": null,
      "secondSubject": null,
      "majorCode": "002",
      "majorName": "作曲与作曲技术理论",
      "planCount": "不编制分省计划",
      "durationYears": 5,
      "tuitionPerYear": "免费",
      "campus": null,
      "remarks": "戏曲作曲河北梆子 艺术校考类,5年,免费",
      "pdfPage": 51,
      "bookPage": 3
    },
    {
      "batchName": "本科提前批艺术类本科第一批",
      "schoolCode": "10049",
      "schoolName": "中国戏曲学院",
      "schoolTotalPlan": null,
      "schoolLocation": "北京市",
      "consultPhone": "010-63339858",
      "majorGroupCode": "201",
      "majorGroupPlan": null,
      "firstSubject": null,
      "secondSubject": null,
      "majorCode": "003",
      "majorName": "作曲与作曲技术理论",
      "planCount": "不编制分省计划",
      "durationYears": 5,
      "tuitionPerYear": "免费",
      "campus": null,
      "remarks": "戏曲作曲黄梅戏 艺术校考类,5年，免费",
      "pdfPage": 51,
      "bookPage": 3
    },
    {
      "batchName": "本科提前批艺术类本科第一批",
      "schoolCode": "10049",
      "schoolName": "中国戏曲学院",
      "schoolTotalPlan": null,
      "schoolLocation": "北京市",
      "consultPhone": "010-63339858",
      "majorGroupCode": "201",
      "majorGroupPlan": null,
      "firstSubject": null,
      "secondSubject": null,
      "majorCode": "004",
      "majorName": "作曲与作曲技术理论",
      "planCount": "不编制分省计划",
      "durationYears": 5,
      "tuitionPerYear": "免费",
      "campus": null,
      "remarks": "戏曲作曲京剧 艺术校考类,5年,免费",
      "pdfPage": 51,
      "bookPage": 3
    },
    {
      "batchName": "本科提前批艺术类本科第一批",
      "schoolCode": "10049",
      "schoolName": "中国戏曲学院",
      "schoolTotalPlan": null,
      "schoolLocation": "北京市",
      "consultPhone": "010-63339858",
      "majorGroupCode": "201",
      "majorGroupPlan": null,
      "firstSubject": null,
      "secondSubject": null,
      "majorCode": "005",
      "majorName": "作曲与作曲技术理论",
      "planCount": "不编制分省计划",
      "durationYears": 5,
      "tuitionPerYear": "免费",
      "campus": null,
      "remarks": "戏曲作曲昆曲 艺术校考类,5年,免费",
      "pdfPage": 51,
      "bookPage": 3
    },
    {
      "batchName": "本科提前批艺术类本科第一批",
      "schoolCode": "10049",
      "schoolName": "中国戏曲学院",
      "schoolTotalPlan": null,
      "schoolLocation": "北京市",
      "consultPhone": "010-63339858",
      "majorGroupCode": "201",
      "majorGroupPlan": null,
      "firstSubject": null,
      "secondSubject": null,
      "majorCode": "006",
      "majorName": "作曲与作曲技术理论",
      "planCount": "不编制分省计划",
      "durationYears": 5,
      "tuitionPerYear": "免费",
      "campus": null,
      "remarks": "戏曲作曲评剧 艺术校考类,5年,免费",
      "pdfPage": 51,
      "bookPage": 3
    },
    {
      "batchName": "本科提前批艺术类本科第一批",
      "schoolCode": "10049",
      "schoolName": "中国戏曲学院",
      "schoolTotalPlan": null,
      "schoolLocation": "北京市",
      "consultPhone": "010-63339858",
      "majorGroupCode": "201",
      "majorGroupPlan": null,
      "firstSubject": null,
      "secondSubject": null,
      "majorCode": "007",
      "majorName": "作曲与作曲技术理论",
      "planCount": "不编制分省计划",
      "durationYears": 5,
      "tuitionPerYear": "免费",
      "campus": null,
      "remarks": "戏曲作曲豫剧 艺术校考类,5年,免费",
      "pdfPage": 51,
      "bookPage": 3
    },
    {
      "batchName": "本科提前批艺术类本科第一批",
      "schoolCode": "10049",
      "schoolName": "中国戏曲学院",
      "schoolTotalPlan": null,
      "schoolLocation": "北京市",
      "consultPhone": "010-63339858",
      "majorGroupCode": "201",
      "majorGroupPlan": null,
      "firstSubject": null,
      "secondSubject": null,
      "majorCode": "008",
      "majorName": "表演",
      "planCount": "不编制分省计划",
      "durationYears": 4,
      "tuitionPerYear": "免费",
      "campus": null,
      "remarks": "地方剧种表演福建莆仙戏 艺术校考类，4年，免费",
      "pdfPage": 51,
      "bookPage": 3
    },
    {
      "batchName": "本科提前批艺术类本科第一批",
      "schoolCode": "10049",
      "schoolName": "中国戏曲学院",
      "schoolTotalPlan": null,
      "schoolLocation": "北京市",
      "consultPhone": "010-63339858",
      "majorGroupCode": "201",
      "majorGroupPlan": null,
      "firstSubject": null,
      "secondSubject": null,
      "majorCode": "009",
      "majorName": "表演",
      "planCount": "不编制分省计划",
      "durationYears": 4,
      "tuitionPerYear": "免费",
      "campus": null,
      "remarks": "地方剧种表演广东汉剧 艺术校考类，4年，免费",
      "pdfPage": 51,
      "bookPage": 3
    },
    {
      "batchName": "本科提前批艺术类本科第一批",
      "schoolCode": "10049",
      "schoolName": "中国戏曲学院",
      "schoolTotalPlan": null,
      "schoolLocation": "北京市",
      "consultPhone": "010-63339858",
      "majorGroupCode": "201",
      "majorGroupPlan": null,
      "firstSubject": null,
      "secondSubject": null,
      "majorCode": "010",
      "majorName": "表演",
      "planCount": "不编制分省计划",
      "durationYears": 4,
      "tuitionPerYear": "免费",
      "campus": null,
      "remarks": "地方剧种表演河南曲剧 艺术校考类,4年,免费",
      "pdfPage": 51,
      "bookPage": 3
    },
    {
      "batchName": "本科提前批艺术类本科第一批",
      "schoolCode": "10049",
      "schoolName": "中国戏曲学院",
      "schoolTotalPlan": null,
      "schoolLocation": "北京市",
      "consultPhone": "010-63339858",
      "majorGroupCode": "201",
      "majorGroupPlan": null,
      "firstSubject": null,
      "secondSubject": null,
      "majorCode": "011",
      "majorName": "表演",
      "planCount": "不编制分省计划",
      "durationYears": 4,
      "tuitionPerYear": "免费",
      "campus": null,
      "remarks": "京剧表演 艺术校考类,4年,免费",
      "pdfPage": 51,
      "bookPage": 3
    },
    {
      "batchName": "本科提前批艺术类本科第一批",
      "schoolCode": "10049",
      "schoolName": "中国戏曲学院",
      "schoolTotalPlan": null,
      "schoolLocation": "北京市",
      "consultPhone": "010-63339858",
      "majorGroupCode": "201",
      "majorGroupPlan": null,
      "firstSubject": null,
      "secondSubject": null,
      "majorCode": "012",
      "majorName": "表演",
      "planCount": "不编制分省计划",
      "durationYears": 4,
      "tuitionPerYear": "免费",
      "campus": null,
      "remarks": "京剧器乐 艺术校考类,4年,免费",
      "pdfPage": 51,
      "bookPage": 3
    },
    {
      "batchName": "本科提前批艺术类本科第一批",
      "schoolCode": "10049",
      "schoolName": "中国戏曲学院",
      "schoolTotalPlan": null,
      "schoolLocation": "北京市",
      "consultPhone": "010-63339858",
      "majorGroupCode": "201",
      "majorGroupPlan": null,
      "firstSubject": null,
      "secondSubject": null,
      "majorCode": "013",
      "majorName": "表演",
      "planCount": "不编制分省计划",
      "durationYears": 4,
      "tuitionPerYear": "免费",
      "campus": null,
      "remarks": "昆曲表演 艺术校考类,4年,免费",
      "pdfPage": 52,
      "bookPage": 4
    },
    {
      "batchName": "本科提前批艺术类本科第一批",
      "schoolCode": "10049",
      "schoolName": "中国戏曲学院",
      "schoolTotalPlan": null,
      "schoolLocation": "北京市",
      "consultPhone": "010-63339858",
      "majorGroupCode": "201",
      "majorGroupPlan": null,
      "firstSubject": null,
      "secondSubject": null,
      "majorCode": "014",
      "majorName": "表演",
      "planCount": "不编制分省计划",
      "durationYears": 4,
      "tuitionPerYear": "免费",
      "campus": null,
      "remarks": "昆曲器乐 艺术校考类,4年,免费",
      "pdfPage": 52,
      "bookPage": 4
    },
    {
      "batchName": "本科提前批艺术类本科第一批",
      "schoolCode": "10049",
      "schoolName": "中国戏曲学院",
      "schoolTotalPlan": null,
      "schoolLocation": "北京市",
      "consultPhone": "010-63339858",
      "majorGroupCode": "201",
      "majorGroupPlan": null,
      "firstSubject": null,
      "secondSubject": null,
      "majorCode": "015",
      "majorName": "表演",
      "planCount": "不编制分省计划",
      "durationYears": 4,
      "tuitionPerYear": "免费",
      "campus": null,
      "remarks": "戏曲舞台监督 艺术校考类, 4 年, 免费",
      "pdfPage": 52,
      "bookPage": 4
    },
    {
      "batchName": "本科提前批艺术类本科第一批",
      "schoolCode": "10049",
      "schoolName": "中国戏曲学院",
      "schoolTotalPlan": null,
      "schoolLocation": "北京市",
      "consultPhone": "010-63339858",
      "majorGroupCode": "201",
      "majorGroupPlan": null,
      "firstSubject": null,
      "secondSubject": null,
      "majorCode": "016",
      "majorName": "表演",
      "planCount": "不编制分省计划",
      "durationYears": 4,
      "tuitionPerYear": 10000,
      "campus": null,
      "remarks": "戏曲形体 艺术校考类,4年,10000元/年",
      "pdfPage": 52,
      "bookPage": 4
    },
    {
      "batchName": "本科提前批艺术类本科第一批",
      "schoolCode": "10049",
      "schoolName": "中国戏曲学院",
      "schoolTotalPlan": null,
      "schoolLocation": "北京市",
      "consultPhone": "010-63339858",
      "majorGroupCode": "201",
      "majorGroupPlan": null,
      "firstSubject": null,
      "secondSubject": null,
      "majorCode": "017",
      "majorName": "戏剧影视导演",
      "planCount": "不编制分省计划",
      "durationYears": 4,
      "tuitionPerYear": 10000,
      "campus": null,
      "remarks": "戏曲导演 艺术校考类,4年,10000元/年",
      "pdfPage": 52,
      "bookPage": 4
    }
  ]
}
