{
  "school": {
    "schoolCode": "10143",
    "schoolName": "沈阳航空航天大学",
    "schoolTotalPlan": 62,
    "schoolLocation": "辽宁省沈阳市",
    "consultPhone": "024-89724466",
    "programCount": 32
  },
  "programs": [
    {
      "batchName": "本科普通批",
      "schoolCode": "10143",
      "schoolName": "沈阳航空航天大学",
      "schoolTotalPlan": 62,
      "schoolLocation": "辽宁省沈阳市",
      "consultPhone": "024-89724466",
      "majorGroupCode": "101",
      "majorGroupPlan": 58,
      "firstSubject": "物理",
      "secondSubject": "化学",
      "majorCode": "001",
      "majorName": "机械设计制造及其自动化",
      "planCount": 4,
      "durationYears": 4,
      "tuitionPerYear": 5200,
      "campus": null,
      "remarks": "4年,5200元/年",
      "pdfPage": 167,
      "bookPage": 119
    },
    {
      "batchName": "本科普通批",
      "schoolCode": "10143",
      "schoolName": "沈阳航空航天大学",
      "schoolTotalPlan": 62,
      "schoolLocation": "辽宁省沈阳市",
      "consultPhone": "024-89724466",
      "majorGroupCode": "101",
      "majorGroupPlan": 58,
      "firstSubject": "物理",
      "secondSubject": "化学",
      "majorCode": "002",
      "majorName": "材料成型及控制工程",
      "planCount": 2,
      "durationYears": 4,
      "tuitionPerYear": 5200,
      "campus": null,
      "remarks": "4年,5200元/年",
      "pdfPage": 167,
      "bookPage": 119
    },
    {
      "batchName": "本科普通批",
      "schoolCode": "10143",
      "schoolName": "沈阳航空航天大学",
      "schoolTotalPlan": 62,
      "schoolLocation": "辽宁省沈阳市",
      "consultPhone": "024-89724466",
      "majorGroupCode": "101",
      "majorGroupPlan": 58,
      "firstSubject": "物理",
      "secondSubject": "化学",
      "majorCode": "003",
      "majorName": "机械电子工程",
      "planCount": 1,
      "durationYears": 4,
      "tuitionPerYear": 5200,
      "campus": null,
      "remarks": "4年,5200元/年",
      "pdfPage": 167,
      "bookPage": 119
    },
    {
      "batchName": "本科普通批",
      "schoolCode": "10143",
      "schoolName": "沈阳航空航天大学",
      "schoolTotalPlan": 62,
      "schoolLocation": "辽宁省沈阳市",
      "consultPhone": "024-89724466",
      "majorGroupCode": "101",
      "majorGroupPlan": 58,
      "firstSubject": "物理",
      "secondSubject": "化学",
      "majorCode": "004",
      "majorName": "工业设计",
      "planCount": 1,
      "durationYears": 4,
      "tuitionPerYear": 5200,
      "campus": null,
      "remarks": "4年,5200元/年,考生需要具备一定的美术基础，不具备美术基础的考生填报",
      "pdfPage": 167,
      "bookPage": 119
    },
    {
      "batchName": "本科普通批",
      "schoolCode": "10143",
      "schoolName": "沈阳航空航天大学",
      "schoolTotalPlan": 62,
      "schoolLocation": "辽宁省沈阳市",
      "consultPhone": "024-89724466",
      "majorGroupCode": "101",
      "majorGroupPlan": 58,
      "firstSubject": "物理",
      "secondSubject": "化学",
      "majorCode": "005",
      "majorName": "智能制造工程",
      "planCount": 1,
      "durationYears": 4,
      "tuitionPerYear": 5200,
      "campus": null,
      "remarks": "4年,5200元/年",
      "pdfPage": 167,
      "bookPage": 119
    },
    {
      "batchName": "本科普通批",
      "schoolCode": "10143",
      "schoolName": "沈阳航空航天大学",
      "schoolTotalPlan": 62,
      "schoolLocation": "辽宁省沈阳市",
      "consultPhone": "024-89724466",
      "majorGroupCode": "101",
      "majorGroupPlan": 58,
      "firstSubject": "物理",
      "secondSubject": "化学",
      "majorCode": "006",
      "majorName": "测控技术与仪器",
      "planCount": 1,
      "durationYears": 4,
      "tuitionPerYear": 5200,
      "campus": null,
      "remarks": "4年,5200元/年",
      "pdfPage": 167,
      "bookPage": 119
    },
    {
      "batchName": "本科普通批",
      "schoolCode": "10143",
      "schoolName": "沈阳航空航天大学",
      "schoolTotalPlan": 62,
      "schoolLocation": "辽宁省沈阳市",
      "consultPhone": "024-89724466",
      "majorGroupCode": "101",
      "majorGroupPlan": 58,
      "firstSubject": "物理",
      "secondSubject": "化学",
      "majorCode": "007",
      "majorName": "金属材料工程",
      "planCount": 6,
      "durationYears": 4,
      "tuitionPerYear": 5200,
      "campus": null,
      "remarks": "4年,5200元/年",
      "pdfPage": 167,
      "bookPage": 119
    },
    {
      "batchName": "本科普通批",
      "schoolCode": "10143",
      "schoolName": "沈阳航空航天大学",
      "schoolTotalPlan": 62,
      "schoolLocation": "辽宁省沈阳市",
      "consultPhone": "024-89724466",
      "majorGroupCode": "101",
      "majorGroupPlan": 58,
      "firstSubject": "物理",
      "secondSubject": "化学",
      "majorCode": "008",
      "majorName": "复合材料与工程",
      "planCount": 5,
      "durationYears": 4,
      "tuitionPerYear": 5200,
      "campus": null,
      "remarks": "4年,5200元/年",
      "pdfPage": 167,
      "bookPage": 119
    },
    {
      "batchName": "本科普通批",
      "schoolCode": "10143",
      "schoolName": "沈阳航空航天大学",
      "schoolTotalPlan": 62,
      "schoolLocation": "辽宁省沈阳市",
      "consultPhone": "024-89724466",
      "majorGroupCode": "101",
      "majorGroupPlan": 58,
      "firstSubject": "物理",
      "secondSubject": "化学",
      "majorCode": "009",
      "majorName": "能源与动力工程",
      "planCount": 1,
      "durationYears": 4,
      "tuitionPerYear": 5200,
      "campus": null,
      "remarks": "4年,5200元/年",
      "pdfPage": 167,
      "bookPage": 119
    },
    {
      "batchName": "本科普通批",
      "schoolCode": "10143",
      "schoolName": "沈阳航空航天大学",
      "schoolTotalPlan": 62,
      "schoolLocation": "辽宁省沈阳市",
      "consultPhone": "024-89724466",
      "majorGroupCode": "101",
      "majorGroupPlan": 58,
      "firstSubject": "物理",
      "secondSubject": "化学",
      "majorCode": "010",
      "majorName": "新能源科学与工程",
      "planCount": 4,
      "durationYears": 4,
      "tuitionPerYear": 5200,
      "campus": null,
      "remarks": "4年,5200元/年",
      "pdfPage": 167,
      "bookPage": 119
    },
    {
      "batchName": "本科普通批",
      "schoolCode": "10143",
      "schoolName": "沈阳航空航天大学",
      "schoolTotalPlan": 62,
      "schoolLocation": "辽宁省沈阳市",
      "consultPhone": "024-89724466",
      "majorGroupCode": "101",
      "majorGroupPlan": 58,
      "firstSubject": "物理",
      "secondSubject": "化学",
      "majorCode": "011",
      "majorName": "电子信息工程",
      "planCount": 1,
      "durationYears": 4,
      "tuitionPerYear": 5200,
      "campus": null,
      "remarks": "4年,5200元/年",
      "pdfPage": 167,
      "bookPage": 119
    },
    {
      "batchName": "本科普通批",
      "schoolCode": "10143",
      "schoolName": "沈阳航空航天大学",
      "schoolTotalPlan": 62,
      "schoolLocation": "辽宁省沈阳市",
      "consultPhone": "024-89724466",
      "majorGroupCode": "101",
      "majorGroupPlan": 58,
      "firstSubject": "物理",
      "secondSubject": "化学",
      "majorCode": "012",
      "majorName": "通信工程",
      "planCount": 1,
      "durationYears": 4,
      "tuitionPerYear": 5200,
      "campus": null,
      "remarks": "4年,5200元/年",
      "pdfPage": 167,
      "bookPage": 119
    },
    {
      "batchName": "本科普通批",
      "schoolCode": "10143",
      "schoolName": "沈阳航空航天大学",
      "schoolTotalPlan": 62,
      "schoolLocation": "辽宁省沈阳市",
      "consultPhone": "024-89724466",
      "majorGroupCode": "101",
      "majorGroupPlan": 58,
      "firstSubject": "物理",
      "secondSubject": "化学",
      "majorCode": "013",
      "majorName": "人工智能",
      "planCount": 1,
      "durationYears": 4,
      "tuitionPerYear": 5200,
      "campus": null,
      "remarks": "4年,5200元/年",
      "pdfPage": 167,
      "bookPage": 119
    },
    {
      "batchName": "本科普通批",
      "schoolCode": "10143",
      "schoolName": "沈阳航空航天大学",
      "schoolTotalPlan": 62,
      "schoolLocation": "辽宁省沈阳市",
      "consultPhone": "024-89724466",
      "majorGroupCode": "101",
      "majorGroupPlan": 58,
      "firstSubject": "物理",
      "secondSubject": "化学",
      "majorCode": "014",
      "majorName": "自动化",
      "planCount": 2,
      "durationYears": 4,
      "tuitionPerYear": 5200,
      "campus": null,
      "remarks": "4年,5200元/年",
      "pdfPage": 167,
      "bookPage": 119
    },
    {
      "batchName": "本科普通批",
      "schoolCode": "10143",
      "schoolName": "沈阳航空航天大学",
      "schoolTotalPlan": 62,
      "schoolLocation": "辽宁省沈阳市",
      "consultPhone": "024-89724466",
      "majorGroupCode": "101",
      "majorGroupPlan": 58,
      "firstSubject": "物理",
      "secondSubject": "化学",
      "majorCode": "015",
      "majorName": "机器人工程",
      "planCount": 1,
      "durationYears": 4,
      "tuitionPerYear": 5200,
      "campus": null,
      "remarks": "4年,5200元/年",
      "pdfPage": 167,
      "bookPage": 119
    },
    {
      "batchName": "本科普通批",
      "schoolCode": "10143",
      "schoolName": "沈阳航空航天大学",
      "schoolTotalPlan": 62,
      "schoolLocation": "辽宁省沈阳市",
      "consultPhone": "024-89724466",
      "majorGroupCode": "101",
      "majorGroupPlan": 58,
      "firstSubject": "物理",
      "secondSubject": "化学",
      "majorCode": "016",
      "majorName": "计算机科学与技术",
      "planCount": 1,
      "durationYears": 4,
      "tuitionPerYear": 5200,
      "campus": null,
      "remarks": "4年,5200元/年",
      "pdfPage": 167,
      "bookPage": 119
    },
    {
      "batchName": "本科普通批",
      "schoolCode": "10143",
      "schoolName": "沈阳航空航天大学",
      "schoolTotalPlan": 62,
      "schoolLocation": "辽宁省沈阳市",
      "consultPhone": "024-89724466",
      "majorGroupCode": "101",
      "majorGroupPlan": 58,
      "firstSubject": "物理",
      "secondSubject": "化学",
      "majorCode": "017",
      "majorName": "软件工程",
      "planCount": 1,
      "durationYears": 4,
      "tuitionPerYear": 5200,
      "campus": null,
      "remarks": "4年,5200元/年",
      "pdfPage": 167,
      "bookPage": 119
    },
    {
      "batchName": "本科普通批",
      "schoolCode": "10143",
      "schoolName": "沈阳航空航天大学",
      "schoolTotalPlan": 62,
      "schoolLocation": "辽宁省沈阳市",
      "consultPhone": "024-89724466",
      "majorGroupCode": "101",
      "majorGroupPlan": 58,
      "firstSubject": "物理",
      "secondSubject": "化学",
      "majorCode": "018",
      "majorName": "网络工程",
      "planCount": 1,
      "durationYears": 4,
      "tuitionPerYear": 5200,
      "campus": null,
      "remarks": "4年,5200元/年",
      "pdfPage": 167,
      "bookPage": 119
    },
    {
      "batchName": "本科普通批",
      "schoolCode": "10143",
      "schoolName": "沈阳航空航天大学",
      "schoolTotalPlan": 62,
      "schoolLocation": "辽宁省沈阳市",
      "consultPhone": "024-89724466",
      "majorGroupCode": "101",
      "majorGroupPlan": 58,
      "firstSubject": "物理",
      "secondSubject": "化学",
      "majorCode": "019",
      "majorName": "数据科学与大数据技术",
      "planCount": 1,
      "durationYears": 4,
      "tuitionPerYear": 5200,
      "campus": null,
      "remarks": "4年,5200元/年",
      "pdfPage": 167,
      "bookPage": 119
    },
    {
      "batchName": "本科普通批",
      "schoolCode": "10143",
      "schoolName": "沈阳航空航天大学",
      "schoolTotalPlan": 62,
      "schoolLocation": "辽宁省沈阳市",
      "consultPhone": "024-89724466",
      "majorGroupCode": "101",
      "majorGroupPlan": 58,
      "firstSubject": "物理",
      "secondSubject": "化学",
      "majorCode": "020",
      "majorName": "交通运输",
      "planCount": 1,
      "durationYears": 4,
      "tuitionPerYear": 5200,
      "campus": null,
      "remarks": "4年,5200元/年,学校外语课程采用英语教学，请英语语种以外的其他语种考生填报",
      "pdfPage": 167,
      "bookPage": 119
    },
    {
      "batchName": "本科普通批",
      "schoolCode": "10143",
      "schoolName": "沈阳航空航天大学",
      "schoolTotalPlan": 62,
      "schoolLocation": "辽宁省沈阳市",
      "consultPhone": "024-89724466",
      "majorGroupCode": "101",
      "majorGroupPlan": 58,
      "firstSubject": "物理",
      "secondSubject": "化学",
      "majorCode": "021",
      "majorName": "航空航天工程",
      "planCount": 1,
      "durationYears": 4,
      "tuitionPerYear": 5200,
      "campus": null,
      "remarks": "4年,5200元/年",
      "pdfPage": 167,
      "bookPage": 119
    },
    {
      "batchName": "本科普通批",
      "schoolCode": "10143",
      "schoolName": "沈阳航空航天大学",
      "schoolTotalPlan": 62,
      "schoolLocation": "辽宁省沈阳市",
      "consultPhone": "024-89724466",
      "majorGroupCode": "101",
      "majorGroupPlan": 58,
      "firstSubject": "物理",
      "secondSubject": "化学",
      "majorCode": "022",
      "majorName": "飞行器设计与工程",
      "planCount": 1,
      "durationYears": 4,
      "tuitionPerYear": 5200,
      "campus": null,
      "remarks": "4年,5200元/年",
      "pdfPage": 167,
      "bookPage": 119
    },
    {
      "batchName": "本科普通批",
      "schoolCode": "10143",
      "schoolName": "沈阳航空航天大学",
      "schoolTotalPlan": 62,
      "schoolLocation": "辽宁省沈阳市",
      "consultPhone": "024-89724466",
      "majorGroupCode": "101",
      "majorGroupPlan": 58,
      "firstSubject": "物理",
      "secondSubject": "化学",
      "majorCode": "023",
      "majorName": "飞行器制造工程",
      "planCount": 4,
      "durationYears": 4,
      "tuitionPerYear": 5200,
      "campus": null,
      "remarks": "4年,5200元/年",
      "pdfPage": 167,
      "bookPage": 119
    },
    {
      "batchName": "本科普通批",
      "schoolCode": "10143",
      "schoolName": "沈阳航空航天大学",
      "schoolTotalPlan": 62,
      "schoolLocation": "辽宁省沈阳市",
      "consultPhone": "024-89724466",
      "majorGroupCode": "101",
      "majorGroupPlan": 58,
      "firstSubject": "物理",
      "secondSubject": "化学",
      "majorCode": "024",
      "majorName": "飞行器动力工程",
      "planCount": 2,
      "durationYears": 4,
      "tuitionPerYear": 5200,
      "campus": null,
      "remarks": "4年,5200元/年",
      "pdfPage": 167,
      "bookPage": 119
    },
    {
      "batchName": "本科普通批",
      "schoolCode": "10143",
      "schoolName": "沈阳航空航天大学",
      "schoolTotalPlan": 62,
      "schoolLocation": "辽宁省沈阳市",
      "consultPhone": "024-89724466",
      "majorGroupCode": "101",
      "majorGroupPlan": 58,
      "firstSubject": "物理",
      "secondSubject": "化学",
      "majorCode": "025",
      "majorName": "飞行器质量与可靠性",
      "planCount": 2,
      "durationYears": 4,
      "tuitionPerYear": 5200,
      "campus": null,
      "remarks": "4年,5200元/年,学校外语课程采用英语教学，请英语语种以外的其他语种考生填报",
      "pdfPage": 167,
      "bookPage": 119
    },
    {
      "batchName": "本科普通批",
      "schoolCode": "10143",
      "schoolName": "沈阳航空航天大学",
      "schoolTotalPlan": 62,
      "schoolLocation": "辽宁省沈阳市",
      "consultPhone": "024-89724466",
      "majorGroupCode": "101",
      "majorGroupPlan": 58,
      "firstSubject": "物理",
      "secondSubject": "化学",
      "majorCode": "026",
      "majorName": "飞行器适航技术",
      "planCount": 1,
      "durationYears": 4,
      "tuitionPerYear": 5200,
      "campus": null,
      "remarks": "4年,5200元/年",
      "pdfPage": 167,
      "bookPage": 119
    },
    {
      "batchName": "本科普通批",
      "schoolCode": "10143",
      "schoolName": "沈阳航空航天大学",
      "schoolTotalPlan": 62,
      "schoolLocation": "辽宁省沈阳市",
      "consultPhone": "024-89724466",
      "majorGroupCode": "101",
      "majorGroupPlan": 58,
      "firstSubject": "物理",
      "secondSubject": "化学",
      "majorCode": "027",
      "majorName": "探测制导与控制技术",
      "planCount": 1,
      "durationYears": 4,
      "tuitionPerYear": 5200,
      "campus": null,
      "remarks": "4年,5200元/年",
      "pdfPage": 167,
      "bookPage": 119
    },
    {
      "batchName": "本科普通批",
      "schoolCode": "10143",
      "schoolName": "沈阳航空航天大学",
      "schoolTotalPlan": 62,
      "schoolLocation": "辽宁省沈阳市",
      "consultPhone": "024-89724466",
      "majorGroupCode": "101",
      "majorGroupPlan": 58,
      "firstSubject": "物理",
      "secondSubject": "化学",
      "majorCode": "028",
      "majorName": "安全工程",
      "planCount": 2,
      "durationYears": 4,
      "tuitionPerYear": 5200,
      "campus": null,
      "remarks": "4年,5200元/年",
      "pdfPage": 167,
      "bookPage": 119
    },
    {
      "batchName": "本科普通批",
      "schoolCode": "10143",
      "schoolName": "沈阳航空航天大学",
      "schoolTotalPlan": 62,
      "schoolLocation": "辽宁省沈阳市",
      "consultPhone": "024-89724466",
      "majorGroupCode": "101",
      "majorGroupPlan": 58,
      "firstSubject": "物理",
      "secondSubject": "化学",
      "majorCode": "029",
      "majorName": "消防工程",
      "planCount": 5,
      "durationYears": 4,
      "tuitionPerYear": 5200,
      "campus": null,
      "remarks": "4年,5200元/年",
      "pdfPage": 167,
      "bookPage": 119
    },
    {
      "batchName": "本科普通批",
      "schoolCode": "10143",
      "schoolName": "沈阳航空航天大学",
      "schoolTotalPlan": 62,
      "schoolLocation": "辽宁省沈阳市",
      "consultPhone": "024-89724466",
      "majorGroupCode": "101",
      "majorGroupPlan": 58,
      "firstSubject": "物理",
      "secondSubject": "化学",
      "majorCode": "030",
      "majorName": "碳中和科学与工程",
      "planCount": 2,
      "durationYears": 4,
      "tuitionPerYear": 5200,
      "campus": null,
      "remarks": "4年,5200元/年",
      "pdfPage": 167,
      "bookPage": 119
    },
    {
      "batchName": "本科普通批",
      "schoolCode": "10143",
      "schoolName": "沈阳航空航天大学",
      "schoolTotalPlan": 62,
      "schoolLocation": "辽宁省沈阳市",
      "consultPhone": "024-89724466",
      "majorGroupCode": "102",
      "majorGroupPlan": 4,
      "firstSubject": "物理",
      "secondSubject": "不限",
      "majorCode": "031",
      "majorName": "国际经济与贸易",
      "planCount": 2,
      "durationYears": 4,
      "tuitionPerYear": 5200,
      "campus": null,
      "remarks": "4年,5200元/年",
      "pdfPage": 167,
      "bookPage": 119
    },
    {
      "batchName": "本科普通批",
      "schoolCode": "10143",
      "schoolName": "沈阳航空航天大学",
      "schoolTotalPlan": 62,
      "schoolLocation": "辽宁省沈阳市",
      "consultPhone": "024-89724466",
      "majorGroupCode": "102",
      "majorGroupPlan": 4,
      "firstSubject": "物理",
      "secondSubject": "不限",
      "majorCode": "032",
      "majorName": "物流管理",
      "planCount": 2,
      "durationYears": 4,
      "tuitionPerYear": 5200,
      "campus": null,
      "remarks": "4年,5200元/年",
      "pdfPage": 167,
      "bookPage": 119
    }
  ]
}
