{
  "school": {
    "schoolCode": "10238",
    "schoolName": "齐齐哈尔高等师范专科学校",
    "schoolTotalPlan": 3,
    "schoolLocation": "黑龙江省齐齐哈尔市",
    "consultPhone": "0452-2409077、2409088",
    "programCount": 7
  },
  "programs": [
    {
      "batchName": "高职高专提前批体育类",
      "schoolCode": "10238",
      "schoolName": "齐齐哈尔高等师范专科学校",
      "schoolTotalPlan": 3,
      "schoolLocation": "黑龙江省齐齐哈尔市",
      "consultPhone": "0452-2409077、2409088",
      "majorGroupCode": "104",
      "majorGroupPlan": 3,
      "firstSubject": "物理",
      "secondSubject": "不限",
      "majorCode": "002",
      "majorName": "体育教育",
      "planCount": 3,
      "durationYears": 3,
      "tuitionPerYear": 6000,
      "campus": null,
      "remarks": "体育类，师范类，3 年，6000 元/年",
      "pdfPage": 555,
      "bookPage": 507
    },
    {
      "batchName": "高职高专普通批",
      "schoolCode": "10238",
      "schoolName": "齐齐哈尔高等师范专科学校",
      "schoolTotalPlan": 3,
      "schoolLocation": "黑龙江省齐齐哈尔市",
      "consultPhone": "0452-2409077、2409088",
      "majorGroupCode": "102",
      "majorGroupPlan": 21,
      "firstSubject": "物理",
      "secondSubject": "不限",
      "majorCode": "009",
      "majorName": "新能源汽车技术",
      "planCount": 4,
      "durationYears": 3,
      "tuitionPerYear": 6000,
      "campus": null,
      "remarks": "3 年,6000 元/年",
      "pdfPage": 563,
      "bookPage": 515
    },
    {
      "batchName": "高职高专普通批",
      "schoolCode": "10238",
      "schoolName": "齐齐哈尔高等师范专科学校",
      "schoolTotalPlan": 3,
      "schoolLocation": "黑龙江省齐齐哈尔市",
      "consultPhone": "0452-2409077、2409088",
      "majorGroupCode": "102",
      "majorGroupPlan": 21,
      "firstSubject": "物理",
      "secondSubject": "不限",
      "majorCode": "010",
      "majorName": "高速铁路客运服务",
      "planCount": 3,
      "durationYears": 3,
      "tuitionPerYear": 6000,
      "campus": null,
      "remarks": "3 年,6000 元/年",
      "pdfPage": 563,
      "bookPage": 515
    },
    {
      "batchName": "高职高专普通批",
      "schoolCode": "10238",
      "schoolName": "齐齐哈尔高等师范专科学校",
      "schoolTotalPlan": 3,
      "schoolLocation": "黑龙江省齐齐哈尔市",
      "consultPhone": "0452-2409077、2409088",
      "majorGroupCode": "102",
      "majorGroupPlan": 21,
      "firstSubject": "物理",
      "secondSubject": "不限",
      "majorCode": "011",
      "majorName": "计算机应用技术",
      "planCount": 5,
      "durationYears": 3,
      "tuitionPerYear": 6000,
      "campus": null,
      "remarks": "3 年,6000 元/年",
      "pdfPage": 563,
      "bookPage": 515
    },
    {
      "batchName": "高职高专普通批",
      "schoolCode": "10238",
      "schoolName": "齐齐哈尔高等师范专科学校",
      "schoolTotalPlan": 3,
      "schoolLocation": "黑龙江省齐齐哈尔市",
      "consultPhone": "0452-2409077、2409088",
      "majorGroupCode": "102",
      "majorGroupPlan": 21,
      "firstSubject": "物理",
      "secondSubject": "不限",
      "majorCode": "012",
      "majorName": "人工智能技术应用",
      "planCount": 3,
      "durationYears": 3,
      "tuitionPerYear": 6000,
      "campus": null,
      "remarks": "3 年,6000 元/年",
      "pdfPage": 563,
      "bookPage": 515
    },
    {
      "batchName": "高职高专普通批",
      "schoolCode": "10238",
      "schoolName": "齐齐哈尔高等师范专科学校",
      "schoolTotalPlan": 3,
      "schoolLocation": "黑龙江省齐齐哈尔市",
      "consultPhone": "0452-2409077、2409088",
      "majorGroupCode": "102",
      "majorGroupPlan": 21,
      "firstSubject": "物理",
      "secondSubject": "不限",
      "majorCode": "013",
      "majorName": "小学语文教育",
      "planCount": 3,
      "durationYears": 3,
      "tuitionPerYear": 6000,
      "campus": null,
      "remarks": "师范类,3 年,6000 元/年",
      "pdfPage": 563,
      "bookPage": 515
    },
    {
      "batchName": "高职高专普通批",
      "schoolCode": "10238",
      "schoolName": "齐齐哈尔高等师范专科学校",
      "schoolTotalPlan": 3,
      "schoolLocation": "黑龙江省齐齐哈尔市",
      "consultPhone": "0452-2409077、2409088",
      "majorGroupCode": "102",
      "majorGroupPlan": 21,
      "firstSubject": "物理",
      "secondSubject": "不限",
      "majorCode": "014",
      "majorName": "特殊教育",
      "planCount": 3,
      "durationYears": 3,
      "tuitionPerYear": 4500,
      "campus": null,
      "remarks": "师范类,3 年,4500 元/年",
      "pdfPage": 563,
      "bookPage": 515
    }
  ]
}
