{
  "school": {
    "schoolCode": "11360",
    "schoolName": "攀枝花学院",
    "schoolTotalPlan": 9,
    "schoolLocation": "四川省攀枝花市",
    "consultPhone": "0812-5712507",
    "programCount": 3
  },
  "programs": [
    {
      "batchName": "本科普通批",
      "schoolCode": "11360",
      "schoolName": "攀枝花学院",
      "schoolTotalPlan": 9,
      "schoolLocation": "四川省攀枝花市",
      "consultPhone": "0812-5712507",
      "majorGroupCode": "102",
      "majorGroupPlan": 6,
      "firstSubject": "物理",
      "secondSubject": "化学",
      "majorCode": "002",
      "majorName": "车辆工程",
      "planCount": 3,
      "durationYears": 4,
      "tuitionPerYear": 5980,
      "campus": null,
      "remarks": "4 年,5980 元/年",
      "pdfPage": 413,
      "bookPage": 365
    },
    {
      "batchName": "本科普通批",
      "schoolCode": "11360",
      "schoolName": "攀枝花学院",
      "schoolTotalPlan": 9,
      "schoolLocation": "四川省攀枝花市",
      "consultPhone": "0812-5712507",
      "majorGroupCode": "102",
      "majorGroupPlan": 6,
      "firstSubject": "物理",
      "secondSubject": "化学",
      "majorCode": "003",
      "majorName": "环境工程",
      "planCount": 3,
      "durationYears": 4,
      "tuitionPerYear": 5980,
      "campus": null,
      "remarks": "4年，5980元/年",
      "pdfPage": 413,
      "bookPage": 365
    },
    {
      "batchName": "本科普通批",
      "schoolCode": "11360",
      "schoolName": "攀枝花学院",
      "schoolTotalPlan": 9,
      "schoolLocation": "四川省攀枝花市",
      "consultPhone": "0812-5712507",
      "majorGroupCode": "103",
      "majorGroupPlan": 3,
      "firstSubject": "物理",
      "secondSubject": "不限",
      "majorCode": "004",
      "majorName": "工程管理",
      "planCount": 3,
      "durationYears": 4,
      "tuitionPerYear": 5520,
      "campus": null,
      "remarks": "4 年,5520 元/年",
      "pdfPage": 413,
      "bookPage": 365
    }
  ]
}
