{
  "school": {
    "schoolCode": "11502",
    "schoolName": "福州职业技术大学",
    "schoolTotalPlan": 13,
    "schoolLocation": "福建省福州市",
    "consultPhone": "0591-83760662、83760669",
    "programCount": 10
  },
  "programs": [
    {
      "batchName": "高职高专普通批",
      "schoolCode": "11502",
      "schoolName": "福州职业技术大学",
      "schoolTotalPlan": 13,
      "schoolLocation": "福建省福州市",
      "consultPhone": "0591-83760662、83760669",
      "majorGroupCode": "102",
      "majorGroupPlan": 13,
      "firstSubject": "物理",
      "secondSubject": "不限",
      "majorCode": "003",
      "majorName": "智能建造技术",
      "planCount": 1,
      "durationYears": 3,
      "tuitionPerYear": 6000,
      "campus": null,
      "remarks": "3 年, 6000 元/年",
      "pdfPage": 575,
      "bookPage": 527
    },
    {
      "batchName": "高职高专普通批",
      "schoolCode": "11502",
      "schoolName": "福州职业技术大学",
      "schoolTotalPlan": 13,
      "schoolLocation": "福建省福州市",
      "consultPhone": "0591-83760662、83760669",
      "majorGroupCode": "102",
      "majorGroupPlan": 13,
      "firstSubject": "物理",
      "secondSubject": "不限",
      "majorCode": "004",
      "majorName": "建筑智能化工程技术",
      "planCount": 1,
      "durationYears": 3,
      "tuitionPerYear": 6000,
      "campus": null,
      "remarks": "3 年，6000 元/年",
      "pdfPage": 575,
      "bookPage": 527
    },
    {
      "batchName": "高职高专普通批",
      "schoolCode": "11502",
      "schoolName": "福州职业技术大学",
      "schoolTotalPlan": 13,
      "schoolLocation": "福建省福州市",
      "consultPhone": "0591-83760662、83760669",
      "majorGroupCode": "102",
      "majorGroupPlan": 13,
      "firstSubject": "物理",
      "secondSubject": "不限",
      "majorCode": "005",
      "majorName": "电梯工程技术",
      "planCount": 2,
      "durationYears": 3,
      "tuitionPerYear": 6000,
      "campus": null,
      "remarks": "3 年，6000 元/年",
      "pdfPage": 575,
      "bookPage": 527
    },
    {
      "batchName": "高职高专普通批",
      "schoolCode": "11502",
      "schoolName": "福州职业技术大学",
      "schoolTotalPlan": 13,
      "schoolLocation": "福建省福州市",
      "consultPhone": "0591-83760662、83760669",
      "majorGroupCode": "102",
      "majorGroupPlan": 13,
      "firstSubject": "物理",
      "secondSubject": "不限",
      "majorCode": "006",
      "majorName": "智能控制技术",
      "planCount": 1,
      "durationYears": 3,
      "tuitionPerYear": 6000,
      "campus": null,
      "remarks": "3 年, 6000 元/年",
      "pdfPage": 575,
      "bookPage": 527
    },
    {
      "batchName": "高职高专普通批",
      "schoolCode": "11502",
      "schoolName": "福州职业技术大学",
      "schoolTotalPlan": 13,
      "schoolLocation": "福建省福州市",
      "consultPhone": "0591-83760662、83760669",
      "majorGroupCode": "102",
      "majorGroupPlan": 13,
      "firstSubject": "物理",
      "secondSubject": "不限",
      "majorCode": "007",
      "majorName": "汽车检测与维修技术",
      "planCount": 1,
      "durationYears": 3,
      "tuitionPerYear": 6000,
      "campus": null,
      "remarks": "3 年，6000 元/年",
      "pdfPage": 575,
      "bookPage": 527
    },
    {
      "batchName": "高职高专普通批",
      "schoolCode": "11502",
      "schoolName": "福州职业技术大学",
      "schoolTotalPlan": 13,
      "schoolLocation": "福建省福州市",
      "consultPhone": "0591-83760662、83760669",
      "majorGroupCode": "102",
      "majorGroupPlan": 13,
      "firstSubject": "物理",
      "secondSubject": "不限",
      "majorCode": "008",
      "majorName": "城市轨道车辆应用技术",
      "planCount": 2,
      "durationYears": 3,
      "tuitionPerYear": 6000,
      "campus": null,
      "remarks": "3 年，6000 元/年",
      "pdfPage": 575,
      "bookPage": 527
    },
    {
      "batchName": "高职高专普通批",
      "schoolCode": "11502",
      "schoolName": "福州职业技术大学",
      "schoolTotalPlan": 13,
      "schoolLocation": "福建省福州市",
      "consultPhone": "0591-83760662、83760669",
      "majorGroupCode": "102",
      "majorGroupPlan": 13,
      "firstSubject": "物理",
      "secondSubject": "不限",
      "majorCode": "009",
      "majorName": "应用电子技术",
      "planCount": 2,
      "durationYears": 3,
      "tuitionPerYear": 6000,
      "campus": null,
      "remarks": "3 年，6000 元/年",
      "pdfPage": 575,
      "bookPage": 527
    },
    {
      "batchName": "高职高专普通批",
      "schoolCode": "11502",
      "schoolName": "福州职业技术大学",
      "schoolTotalPlan": 13,
      "schoolLocation": "福建省福州市",
      "consultPhone": "0591-83760662、83760669",
      "majorGroupCode": "102",
      "majorGroupPlan": 13,
      "firstSubject": "物理",
      "secondSubject": "不限",
      "majorCode": "010",
      "majorName": "人工智能技术应用",
      "planCount": 1,
      "durationYears": 3,
      "tuitionPerYear": 6000,
      "campus": null,
      "remarks": "3 年，6000 元/年",
      "pdfPage": 575,
      "bookPage": 527
    },
    {
      "batchName": "高职高专普通批",
      "schoolCode": "11502",
      "schoolName": "福州职业技术大学",
      "schoolTotalPlan": 13,
      "schoolLocation": "福建省福州市",
      "consultPhone": "0591-83760662、83760669",
      "majorGroupCode": "102",
      "majorGroupPlan": 13,
      "firstSubject": "物理",
      "secondSubject": "不限",
      "majorCode": "011",
      "majorName": "市场营销",
      "planCount": 1,
      "durationYears": 3,
      "tuitionPerYear": 6000,
      "campus": null,
      "remarks": "3 年, 6000 元/年",
      "pdfPage": 575,
      "bookPage": 527
    },
    {
      "batchName": "高职高专普通批",
      "schoolCode": "11502",
      "schoolName": "福州职业技术大学",
      "schoolTotalPlan": 13,
      "schoolLocation": "福建省福州市",
      "consultPhone": "0591-83760662、83760669",
      "majorGroupCode": "102",
      "majorGroupPlan": 13,
      "firstSubject": "物理",
      "secondSubject": "不限",
      "majorCode": "012",
      "majorName": "跨境电子商务",
      "planCount": 1,
      "durationYears": 3,
      "tuitionPerYear": 6000,
      "campus": null,
      "remarks": "3 年，6000 元/年",
      "pdfPage": 575,
      "bookPage": 527
    }
  ]
}
