{
  "school": {
    "schoolCode": "13607",
    "schoolName": "吉林动画学院",
    "schoolTotalPlan": 11,
    "schoolLocation": "吉林省长春市",
    "consultPhone": "0431-87021904、8702191、87011156",
    "programCount": 4
  },
  "programs": [
    {
      "batchName": "本科提前批艺术类本科第二批",
      "schoolCode": "13607",
      "schoolName": "吉林动画学院",
      "schoolTotalPlan": 11,
      "schoolLocation": "吉林省长春市",
      "consultPhone": "0431-87021904、8702191、87011156",
      "majorGroupCode": "206",
      "majorGroupPlan": 11,
      "firstSubject": "物理",
      "secondSubject": "不限",
      "majorCode": "011",
      "majorName": "动画",
      "planCount": 3,
      "durationYears": 4,
      "tuitionPerYear": 31500,
      "campus": null,
      "remarks": "美术与设计类,4 年,31500 元/年,含二维动画、三维动画、新媒体动画、动画策划设计、AI 影像艺术、影视特效方向",
      "pdfPage": 76,
      "bookPage": 28
    },
    {
      "batchName": "本科提前批艺术类本科第二批",
      "schoolCode": "13607",
      "schoolName": "吉林动画学院",
      "schoolTotalPlan": 11,
      "schoolLocation": "吉林省长春市",
      "consultPhone": "0431-87021904、8702191、87011156",
      "majorGroupCode": "206",
      "majorGroupPlan": 11,
      "firstSubject": "物理",
      "secondSubject": "不限",
      "majorCode": "012",
      "majorName": "视觉传达设计",
      "planCount": 2,
      "durationYears": 4,
      "tuitionPerYear": 29500,
      "campus": null,
      "remarks": "美术与设计类,4年,29500元/年,含品牌与数字 IP 设计、动漫游信息设计、数字视觉与 AIGC 创新方向",
      "pdfPage": 76,
      "bookPage": 28
    },
    {
      "batchName": "本科提前批艺术类本科第二批",
      "schoolCode": "13607",
      "schoolName": "吉林动画学院",
      "schoolTotalPlan": 11,
      "schoolLocation": "吉林省长春市",
      "consultPhone": "0431-87021904、8702191、87011156",
      "majorGroupCode": "206",
      "majorGroupPlan": 11,
      "firstSubject": "物理",
      "secondSubject": "不限",
      "majorCode": "013",
      "majorName": "数字媒体艺术",
      "planCount": 3,
      "durationYears": 4,
      "tuitionPerYear": 31500,
      "campus": null,
      "remarks": "美术与设计类,4年,31500元/年,影游动漫融合方向",
      "pdfPage": 76,
      "bookPage": 28
    },
    {
      "batchName": "本科提前批艺术类本科第二批",
      "schoolCode": "13607",
      "schoolName": "吉林动画学院",
      "schoolTotalPlan": 11,
      "schoolLocation": "吉林省长春市",
      "consultPhone": "0431-87021904、8702191、87011156",
      "majorGroupCode": "206",
      "majorGroupPlan": 11,
      "firstSubject": "物理",
      "secondSubject": "不限",
      "majorCode": "014",
      "majorName": "游戏艺术设计",
      "planCount": 3,
      "durationYears": 4,
      "tuitionPerYear": 31500,
      "campus": null,
      "remarks": "美术与设计类,4年,31500元/年",
      "pdfPage": 76,
      "bookPage": 28
    }
  ]
}
