{
  "school": {
    "schoolCode": "14067",
    "schoolName": "柳州城市职业学院",
    "schoolTotalPlan": 1107,
    "schoolLocation": "广西壮族自治区柳州市",
    "consultPhone": "0772-5331029",
    "programCount": 46
  },
  "programs": [
    {
      "batchName": "高职高专普通批",
      "schoolCode": "14067",
      "schoolName": "柳州城市职业学院",
      "schoolTotalPlan": 1107,
      "schoolLocation": "广西壮族自治区柳州市",
      "consultPhone": "0772-5331029",
      "majorGroupCode": "151",
      "majorGroupPlan": 1107,
      "firstSubject": "物理",
      "secondSubject": "不限",
      "majorCode": "047",
      "majorName": "机电一体化技术",
      "planCount": 21,
      "durationYears": 3,
      "tuitionPerYear": 7500,
      "campus": null,
      "remarks": "3 年,7500 元/年,在鹿寨分院办学,不招色盲、色弱考生",
      "pdfPage": 654,
      "bookPage": 606
    },
    {
      "batchName": "高职高专普通批",
      "schoolCode": "14067",
      "schoolName": "柳州城市职业学院",
      "schoolTotalPlan": 1107,
      "schoolLocation": "广西壮族自治区柳州市",
      "consultPhone": "0772-5331029",
      "majorGroupCode": "151",
      "majorGroupPlan": 1107,
      "firstSubject": "物理",
      "secondSubject": "不限",
      "majorCode": "048",
      "majorName": "人物形象设计",
      "planCount": 15,
      "durationYears": 3,
      "tuitionPerYear": 6500,
      "campus": null,
      "remarks": "3 年,6500 元/年,在鹿寨分院办学,不招色盲、色弱考生",
      "pdfPage": 654,
      "bookPage": 606
    },
    {
      "batchName": "高职高专普通批",
      "schoolCode": "14067",
      "schoolName": "柳州城市职业学院",
      "schoolTotalPlan": 1107,
      "schoolLocation": "广西壮族自治区柳州市",
      "consultPhone": "0772-5331029",
      "majorGroupCode": "151",
      "majorGroupPlan": 1107,
      "firstSubject": "物理",
      "secondSubject": "不限",
      "majorCode": "049",
      "majorName": "建筑设计",
      "planCount": 29,
      "durationYears": 3,
      "tuitionPerYear": 6500,
      "campus": null,
      "remarks": "3 年,6500 元/年,不招色盲、色弱考生",
      "pdfPage": 654,
      "bookPage": 606
    },
    {
      "batchName": "高职高专普通批",
      "schoolCode": "14067",
      "schoolName": "柳州城市职业学院",
      "schoolTotalPlan": 1107,
      "schoolLocation": "广西壮族自治区柳州市",
      "consultPhone": "0772-5331029",
      "majorGroupCode": "151",
      "majorGroupPlan": 1107,
      "firstSubject": "物理",
      "secondSubject": "不限",
      "majorCode": "050",
      "majorName": "古建筑工程技术",
      "planCount": 27,
      "durationYears": 3,
      "tuitionPerYear": 7000,
      "campus": null,
      "remarks": "3 年,7000 元/年",
      "pdfPage": 654,
      "bookPage": 606
    },
    {
      "batchName": "高职高专普通批",
      "schoolCode": "14067",
      "schoolName": "柳州城市职业学院",
      "schoolTotalPlan": 1107,
      "schoolLocation": "广西壮族自治区柳州市",
      "consultPhone": "0772-5331029",
      "majorGroupCode": "151",
      "majorGroupPlan": 1107,
      "firstSubject": "物理",
      "secondSubject": "不限",
      "majorCode": "051",
      "majorName": "建筑室内设计",
      "planCount": 21,
      "durationYears": 3,
      "tuitionPerYear": 6500,
      "campus": null,
      "remarks": "3 年,6500 元/年,不招色盲、色弱考生",
      "pdfPage": 654,
      "bookPage": 606
    },
    {
      "batchName": "高职高专普通批",
      "schoolCode": "14067",
      "schoolName": "柳州城市职业学院",
      "schoolTotalPlan": 1107,
      "schoolLocation": "广西壮族自治区柳州市",
      "consultPhone": "0772-5331029",
      "majorGroupCode": "151",
      "majorGroupPlan": 1107,
      "firstSubject": "物理",
      "secondSubject": "不限",
      "majorCode": "052",
      "majorName": "建筑工程技术",
      "planCount": 11,
      "durationYears": 3,
      "tuitionPerYear": 6000,
      "campus": null,
      "remarks": "3 年, 6000 元/年",
      "pdfPage": 655,
      "bookPage": 607
    },
    {
      "batchName": "高职高专普通批",
      "schoolCode": "14067",
      "schoolName": "柳州城市职业学院",
      "schoolTotalPlan": 1107,
      "schoolLocation": "广西壮族自治区柳州市",
      "consultPhone": "0772-5331029",
      "majorGroupCode": "151",
      "majorGroupPlan": 1107,
      "firstSubject": "物理",
      "secondSubject": "不限",
      "majorCode": "053",
      "majorName": "工程造价",
      "planCount": 42,
      "durationYears": 3,
      "tuitionPerYear": 6000,
      "campus": null,
      "remarks": "3 年，6000 元/年",
      "pdfPage": 655,
      "bookPage": 607
    },
    {
      "batchName": "高职高专普通批",
      "schoolCode": "14067",
      "schoolName": "柳州城市职业学院",
      "schoolTotalPlan": 1107,
      "schoolLocation": "广西壮族自治区柳州市",
      "consultPhone": "0772-5331029",
      "majorGroupCode": "151",
      "majorGroupPlan": 1107,
      "firstSubject": "物理",
      "secondSubject": "不限",
      "majorCode": "054",
      "majorName": "市政管网智能检测与维护",
      "planCount": 40,
      "durationYears": 3,
      "tuitionPerYear": 7000,
      "campus": null,
      "remarks": "3 年，7000 元/年",
      "pdfPage": 655,
      "bookPage": 607
    },
    {
      "batchName": "高职高专普通批",
      "schoolCode": "14067",
      "schoolName": "柳州城市职业学院",
      "schoolTotalPlan": 1107,
      "schoolLocation": "广西壮族自治区柳州市",
      "consultPhone": "0772-5331029",
      "majorGroupCode": "151",
      "majorGroupPlan": 1107,
      "firstSubject": "物理",
      "secondSubject": "不限",
      "majorCode": "055",
      "majorName": "数字化设计与制造技术",
      "planCount": 11,
      "durationYears": 3,
      "tuitionPerYear": 7500,
      "campus": null,
      "remarks": "3 年，7500 元/年，不招色盲、色弱考生",
      "pdfPage": 655,
      "bookPage": 607
    },
    {
      "batchName": "高职高专普通批",
      "schoolCode": "14067",
      "schoolName": "柳州城市职业学院",
      "schoolTotalPlan": 1107,
      "schoolLocation": "广西壮族自治区柳州市",
      "consultPhone": "0772-5331029",
      "majorGroupCode": "151",
      "majorGroupPlan": 1107,
      "firstSubject": "物理",
      "secondSubject": "不限",
      "majorCode": "056",
      "majorName": "机电一体化技术",
      "planCount": 41,
      "durationYears": 3,
      "tuitionPerYear": 7500,
      "campus": null,
      "remarks": "3 年，7500 元/年，不招色盲、色弱考生",
      "pdfPage": 655,
      "bookPage": 607
    },
    {
      "batchName": "高职高专普通批",
      "schoolCode": "14067",
      "schoolName": "柳州城市职业学院",
      "schoolTotalPlan": 1107,
      "schoolLocation": "广西壮族自治区柳州市",
      "consultPhone": "0772-5331029",
      "majorGroupCode": "151",
      "majorGroupPlan": 1107,
      "firstSubject": "物理",
      "secondSubject": "不限",
      "majorCode": "057",
      "majorName": "工业机器人技术",
      "planCount": 26,
      "durationYears": 3,
      "tuitionPerYear": 7500,
      "campus": null,
      "remarks": "3 年，7500 元/年，不招色盲、色弱考生",
      "pdfPage": 655,
      "bookPage": 607
    },
    {
      "batchName": "高职高专普通批",
      "schoolCode": "14067",
      "schoolName": "柳州城市职业学院",
      "schoolTotalPlan": 1107,
      "schoolLocation": "广西壮族自治区柳州市",
      "consultPhone": "0772-5331029",
      "majorGroupCode": "151",
      "majorGroupPlan": 1107,
      "firstSubject": "物理",
      "secondSubject": "不限",
      "majorCode": "058",
      "majorName": "电气自动化技术",
      "planCount": 41,
      "durationYears": 3,
      "tuitionPerYear": 6000,
      "campus": null,
      "remarks": "3 年,6000 元/年,不招色盲、色弱考生",
      "pdfPage": 655,
      "bookPage": 607
    },
    {
      "batchName": "高职高专普通批",
      "schoolCode": "14067",
      "schoolName": "柳州城市职业学院",
      "schoolTotalPlan": 1107,
      "schoolLocation": "广西壮族自治区柳州市",
      "consultPhone": "0772-5331029",
      "majorGroupCode": "151",
      "majorGroupPlan": 1107,
      "firstSubject": "物理",
      "secondSubject": "不限",
      "majorCode": "059",
      "majorName": "具身智能机器人技术",
      "planCount": 26,
      "durationYears": 3,
      "tuitionPerYear": 7500,
      "campus": null,
      "remarks": "3 年，7500 元/年",
      "pdfPage": 655,
      "bookPage": 607
    },
    {
      "batchName": "高职高专普通批",
      "schoolCode": "14067",
      "schoolName": "柳州城市职业学院",
      "schoolTotalPlan": 1107,
      "schoolLocation": "广西壮族自治区柳州市",
      "consultPhone": "0772-5331029",
      "majorGroupCode": "151",
      "majorGroupPlan": 1107,
      "firstSubject": "物理",
      "secondSubject": "不限",
      "majorCode": "060",
      "majorName": "无人机应用技术",
      "planCount": 23,
      "durationYears": 3,
      "tuitionPerYear": 7500,
      "campus": null,
      "remarks": "3 年，7500 元/年",
      "pdfPage": 655,
      "bookPage": 607
    },
    {
      "batchName": "高职高专普通批",
      "schoolCode": "14067",
      "schoolName": "柳州城市职业学院",
      "schoolTotalPlan": 1107,
      "schoolLocation": "广西壮族自治区柳州市",
      "consultPhone": "0772-5331029",
      "majorGroupCode": "151",
      "majorGroupPlan": 1107,
      "firstSubject": "物理",
      "secondSubject": "不限",
      "majorCode": "061",
      "majorName": "新能源汽车技术",
      "planCount": 47,
      "durationYears": 3,
      "tuitionPerYear": 7500,
      "campus": null,
      "remarks": "3 年，7500 元/年，不招色盲、色弱考生",
      "pdfPage": 655,
      "bookPage": 607
    },
    {
      "batchName": "高职高专普通批",
      "schoolCode": "14067",
      "schoolName": "柳州城市职业学院",
      "schoolTotalPlan": 1107,
      "schoolLocation": "广西壮族自治区柳州市",
      "consultPhone": "0772-5331029",
      "majorGroupCode": "151",
      "majorGroupPlan": 1107,
      "firstSubject": "物理",
      "secondSubject": "不限",
      "majorCode": "062",
      "majorName": "智能网联汽车技术",
      "planCount": 53,
      "durationYears": 3,
      "tuitionPerYear": 7500,
      "campus": null,
      "remarks": "3 年，7500 元/年",
      "pdfPage": 655,
      "bookPage": 607
    },
    {
      "batchName": "高职高专普通批",
      "schoolCode": "14067",
      "schoolName": "柳州城市职业学院",
      "schoolTotalPlan": 1107,
      "schoolLocation": "广西壮族自治区柳州市",
      "consultPhone": "0772-5331029",
      "majorGroupCode": "151",
      "majorGroupPlan": 1107,
      "firstSubject": "物理",
      "secondSubject": "不限",
      "majorCode": "063",
      "majorName": "汽车技术服务与营销",
      "planCount": 5,
      "durationYears": 3,
      "tuitionPerYear": 6000,
      "campus": null,
      "remarks": "3 年，6000 元/年",
      "pdfPage": 655,
      "bookPage": 607
    },
    {
      "batchName": "高职高专普通批",
      "schoolCode": "14067",
      "schoolName": "柳州城市职业学院",
      "schoolTotalPlan": 1107,
      "schoolLocation": "广西壮族自治区柳州市",
      "consultPhone": "0772-5331029",
      "majorGroupCode": "151",
      "majorGroupPlan": 1107,
      "firstSubject": "物理",
      "secondSubject": "不限",
      "majorCode": "066",
      "majorName": "软件技术",
      "planCount": 37,
      "durationYears": 3,
      "tuitionPerYear": 6000,
      "campus": null,
      "remarks": "3 年，6000 元/年",
      "pdfPage": 655,
      "bookPage": 607
    },
    {
      "batchName": "高职高专普通批",
      "schoolCode": "14067",
      "schoolName": "柳州城市职业学院",
      "schoolTotalPlan": 1107,
      "schoolLocation": "广西壮族自治区柳州市",
      "consultPhone": "0772-5331029",
      "majorGroupCode": "151",
      "majorGroupPlan": 1107,
      "firstSubject": "物理",
      "secondSubject": "不限",
      "majorCode": "064",
      "majorName": "汽车检测与维修技术",
      "planCount": 41,
      "durationYears": 3,
      "tuitionPerYear": 7500,
      "campus": null,
      "remarks": "3 年，7500 元/年",
      "pdfPage": 655,
      "bookPage": 607
    },
    {
      "batchName": "高职高专普通批",
      "schoolCode": "14067",
      "schoolName": "柳州城市职业学院",
      "schoolTotalPlan": 1107,
      "schoolLocation": "广西壮族自治区柳州市",
      "consultPhone": "0772-5331029",
      "majorGroupCode": "151",
      "majorGroupPlan": 1107,
      "firstSubject": "物理",
      "secondSubject": "不限",
      "majorCode": "065",
      "majorName": "计算机网络技术",
      "planCount": 47,
      "durationYears": 3,
      "tuitionPerYear": 6000,
      "campus": null,
      "remarks": "3 年，6000 元/年",
      "pdfPage": 655,
      "bookPage": 607
    },
    {
      "batchName": "高职高专普通批",
      "schoolCode": "14067",
      "schoolName": "柳州城市职业学院",
      "schoolTotalPlan": 1107,
      "schoolLocation": "广西壮族自治区柳州市",
      "consultPhone": "0772-5331029",
      "majorGroupCode": "151",
      "majorGroupPlan": 1107,
      "firstSubject": "物理",
      "secondSubject": "不限",
      "majorCode": "067",
      "majorName": "数字媒体技术",
      "planCount": 27,
      "durationYears": 3,
      "tuitionPerYear": 7500,
      "campus": null,
      "remarks": "3 年，7500 元/年",
      "pdfPage": 655,
      "bookPage": 607
    },
    {
      "batchName": "高职高专普通批",
      "schoolCode": "14067",
      "schoolName": "柳州城市职业学院",
      "schoolTotalPlan": 1107,
      "schoolLocation": "广西壮族自治区柳州市",
      "consultPhone": "0772-5331029",
      "majorGroupCode": "151",
      "majorGroupPlan": 1107,
      "firstSubject": "物理",
      "secondSubject": "不限",
      "majorCode": "068",
      "majorName": "大数据技术",
      "planCount": 27,
      "durationYears": 3,
      "tuitionPerYear": 7500,
      "campus": null,
      "remarks": "3 年，7500 元/年",
      "pdfPage": 655,
      "bookPage": 607
    },
    {
      "batchName": "高职高专普通批",
      "schoolCode": "14067",
      "schoolName": "柳州城市职业学院",
      "schoolTotalPlan": 1107,
      "schoolLocation": "广西壮族自治区柳州市",
      "consultPhone": "0772-5331029",
      "majorGroupCode": "151",
      "majorGroupPlan": 1107,
      "firstSubject": "物理",
      "secondSubject": "不限",
      "majorCode": "069",
      "majorName": "信息安全技术应用",
      "planCount": 37,
      "durationYears": 3,
      "tuitionPerYear": 7500,
      "campus": null,
      "remarks": "3 年，7500 元/年",
      "pdfPage": 655,
      "bookPage": 607
    },
    {
      "batchName": "高职高专普通批",
      "schoolCode": "14067",
      "schoolName": "柳州城市职业学院",
      "schoolTotalPlan": 1107,
      "schoolLocation": "广西壮族自治区柳州市",
      "consultPhone": "0772-5331029",
      "majorGroupCode": "151",
      "majorGroupPlan": 1107,
      "firstSubject": "物理",
      "secondSubject": "不限",
      "majorCode": "070",
      "majorName": "人工智能技术应用",
      "planCount": 47,
      "durationYears": 3,
      "tuitionPerYear": 7500,
      "campus": null,
      "remarks": "3 年，7500 元/年",
      "pdfPage": 655,
      "bookPage": 607
    },
    {
      "batchName": "高职高专普通批",
      "schoolCode": "14067",
      "schoolName": "柳州城市职业学院",
      "schoolTotalPlan": 1107,
      "schoolLocation": "广西壮族自治区柳州市",
      "consultPhone": "0772-5331029",
      "majorGroupCode": "151",
      "majorGroupPlan": 1107,
      "firstSubject": "物理",
      "secondSubject": "不限",
      "majorCode": "071",
      "majorName": "工业软件开发技术",
      "planCount": 27,
      "durationYears": 3,
      "tuitionPerYear": 7500,
      "campus": null,
      "remarks": "3 年，7500 元/年",
      "pdfPage": 655,
      "bookPage": 607
    },
    {
      "batchName": "高职高专普通批",
      "schoolCode": "14067",
      "schoolName": "柳州城市职业学院",
      "schoolTotalPlan": 1107,
      "schoolLocation": "广西壮族自治区柳州市",
      "consultPhone": "0772-5331029",
      "majorGroupCode": "151",
      "majorGroupPlan": 1107,
      "firstSubject": "物理",
      "secondSubject": "不限",
      "majorCode": "072",
      "majorName": "康复治疗技术",
      "planCount": 34,
      "durationYears": 3,
      "tuitionPerYear": 8000,
      "campus": null,
      "remarks": "3 年，8000 元/年",
      "pdfPage": 655,
      "bookPage": 607
    },
    {
      "batchName": "高职高专普通批",
      "schoolCode": "14067",
      "schoolName": "柳州城市职业学院",
      "schoolTotalPlan": 1107,
      "schoolLocation": "广西壮族自治区柳州市",
      "consultPhone": "0772-5331029",
      "majorGroupCode": "151",
      "majorGroupPlan": 1107,
      "firstSubject": "物理",
      "secondSubject": "不限",
      "majorCode": "073",
      "majorName": "健康管理",
      "planCount": 27,
      "durationYears": 3,
      "tuitionPerYear": 8000,
      "campus": null,
      "remarks": "3年，8000元/年",
      "pdfPage": 655,
      "bookPage": 607
    },
    {
      "batchName": "高职高专普通批",
      "schoolCode": "14067",
      "schoolName": "柳州城市职业学院",
      "schoolTotalPlan": 1107,
      "schoolLocation": "广西壮族自治区柳州市",
      "consultPhone": "0772-5331029",
      "majorGroupCode": "151",
      "majorGroupPlan": 1107,
      "firstSubject": "物理",
      "secondSubject": "不限",
      "majorCode": "074",
      "majorName": "婴幼儿托育服务与管理",
      "planCount": 17,
      "durationYears": 3,
      "tuitionPerYear": 8000,
      "campus": null,
      "remarks": "3 年，8000 元/年",
      "pdfPage": 655,
      "bookPage": 607
    },
    {
      "batchName": "高职高专普通批",
      "schoolCode": "14067",
      "schoolName": "柳州城市职业学院",
      "schoolTotalPlan": 1107,
      "schoolLocation": "广西壮族自治区柳州市",
      "consultPhone": "0772-5331029",
      "majorGroupCode": "151",
      "majorGroupPlan": 1107,
      "firstSubject": "物理",
      "secondSubject": "不限",
      "majorCode": "076",
      "majorName": "大数据与会计",
      "planCount": 13,
      "durationYears": 3,
      "tuitionPerYear": 6000,
      "campus": null,
      "remarks": "3 年，6000 元/年",
      "pdfPage": 655,
      "bookPage": 607
    },
    {
      "batchName": "高职高专普通批",
      "schoolCode": "14067",
      "schoolName": "柳州城市职业学院",
      "schoolTotalPlan": 1107,
      "schoolLocation": "广西壮族自治区柳州市",
      "consultPhone": "0772-5331029",
      "majorGroupCode": "151",
      "majorGroupPlan": 1107,
      "firstSubject": "物理",
      "secondSubject": "不限",
      "majorCode": "075",
      "majorName": "大数据与财务管理",
      "planCount": 12,
      "durationYears": 3,
      "tuitionPerYear": 6000,
      "campus": null,
      "remarks": "3 年，6000 元/年",
      "pdfPage": 655,
      "bookPage": 607
    },
    {
      "batchName": "高职高专普通批",
      "schoolCode": "14067",
      "schoolName": "柳州城市职业学院",
      "schoolTotalPlan": 1107,
      "schoolLocation": "广西壮族自治区柳州市",
      "consultPhone": "0772-5331029",
      "majorGroupCode": "151",
      "majorGroupPlan": 1107,
      "firstSubject": "物理",
      "secondSubject": "不限",
      "majorCode": "077",
      "majorName": "业财数据应用与管理",
      "planCount": 12,
      "durationYears": 3,
      "tuitionPerYear": 6500,
      "campus": null,
      "remarks": "3 年，6500 元/年",
      "pdfPage": 655,
      "bookPage": 607
    },
    {
      "batchName": "高职高专普通批",
      "schoolCode": "14067",
      "schoolName": "柳州城市职业学院",
      "schoolTotalPlan": 1107,
      "schoolLocation": "广西壮族自治区柳州市",
      "consultPhone": "0772-5331029",
      "majorGroupCode": "151",
      "majorGroupPlan": 1107,
      "firstSubject": "物理",
      "secondSubject": "不限",
      "majorCode": "079",
      "majorName": "电子商务",
      "planCount": 23,
      "durationYears": 3,
      "tuitionPerYear": 7000,
      "campus": null,
      "remarks": "3年，7000元/年",
      "pdfPage": 655,
      "bookPage": 607
    },
    {
      "batchName": "高职高专普通批",
      "schoolCode": "14067",
      "schoolName": "柳州城市职业学院",
      "schoolTotalPlan": 1107,
      "schoolLocation": "广西壮族自治区柳州市",
      "consultPhone": "0772-5331029",
      "majorGroupCode": "151",
      "majorGroupPlan": 1107,
      "firstSubject": "物理",
      "secondSubject": "不限",
      "majorCode": "080",
      "majorName": "现代物流管理",
      "planCount": 20,
      "durationYears": 3,
      "tuitionPerYear": 6000,
      "campus": null,
      "remarks": "3 年,6000 元/年",
      "pdfPage": 655,
      "bookPage": 607
    },
    {
      "batchName": "高职高专普通批",
      "schoolCode": "14067",
      "schoolName": "柳州城市职业学院",
      "schoolTotalPlan": 1107,
      "schoolLocation": "广西壮族自治区柳州市",
      "consultPhone": "0772-5331029",
      "majorGroupCode": "151",
      "majorGroupPlan": 1107,
      "firstSubject": "物理",
      "secondSubject": "不限",
      "majorCode": "078",
      "majorName": "市场营销",
      "planCount": 12,
      "durationYears": 3,
      "tuitionPerYear": 6000,
      "campus": null,
      "remarks": "3 年，6000 元/年",
      "pdfPage": 655,
      "bookPage": 607
    },
    {
      "batchName": "高职高专普通批",
      "schoolCode": "14067",
      "schoolName": "柳州城市职业学院",
      "schoolTotalPlan": 1107,
      "schoolLocation": "广西壮族自治区柳州市",
      "consultPhone": "0772-5331029",
      "majorGroupCode": "151",
      "majorGroupPlan": 1107,
      "firstSubject": "物理",
      "secondSubject": "不限",
      "majorCode": "081",
      "majorName": "低空物流技术与运营",
      "planCount": 12,
      "durationYears": 3,
      "tuitionPerYear": 6500,
      "campus": null,
      "remarks": "3 年，6500 元/年",
      "pdfPage": 655,
      "bookPage": 607
    },
    {
      "batchName": "高职高专普通批",
      "schoolCode": "14067",
      "schoolName": "柳州城市职业学院",
      "schoolTotalPlan": 1107,
      "schoolLocation": "广西壮族自治区柳州市",
      "consultPhone": "0772-5331029",
      "majorGroupCode": "151",
      "majorGroupPlan": 1107,
      "firstSubject": "物理",
      "secondSubject": "不限",
      "majorCode": "082",
      "majorName": "旅游管理",
      "planCount": 3,
      "durationYears": 3,
      "tuitionPerYear": 5500,
      "campus": null,
      "remarks": "3 年，5500 元/年",
      "pdfPage": 655,
      "bookPage": 607
    },
    {
      "batchName": "高职高专普通批",
      "schoolCode": "14067",
      "schoolName": "柳州城市职业学院",
      "schoolTotalPlan": 1107,
      "schoolLocation": "广西壮族自治区柳州市",
      "consultPhone": "0772-5331029",
      "majorGroupCode": "151",
      "majorGroupPlan": 1107,
      "firstSubject": "物理",
      "secondSubject": "不限",
      "majorCode": "083",
      "majorName": "酒店管理与数字化运营",
      "planCount": 8,
      "durationYears": 3,
      "tuitionPerYear": 6000,
      "campus": null,
      "remarks": "3 年，6000 元/年",
      "pdfPage": 655,
      "bookPage": 607
    },
    {
      "batchName": "高职高专普通批",
      "schoolCode": "14067",
      "schoolName": "柳州城市职业学院",
      "schoolTotalPlan": 1107,
      "schoolLocation": "广西壮族自治区柳州市",
      "consultPhone": "0772-5331029",
      "majorGroupCode": "151",
      "majorGroupPlan": 1107,
      "firstSubject": "物理",
      "secondSubject": "不限",
      "majorCode": "084",
      "majorName": "餐饮智能管理",
      "planCount": 3,
      "durationYears": 3,
      "tuitionPerYear": 7500,
      "campus": null,
      "remarks": "3 年, 7500 元/年",
      "pdfPage": 655,
      "bookPage": 607
    },
    {
      "batchName": "高职高专普通批",
      "schoolCode": "14067",
      "schoolName": "柳州城市职业学院",
      "schoolTotalPlan": 1107,
      "schoolLocation": "广西壮族自治区柳州市",
      "consultPhone": "0772-5331029",
      "majorGroupCode": "151",
      "majorGroupPlan": 1107,
      "firstSubject": "物理",
      "secondSubject": "不限",
      "majorCode": "085",
      "majorName": "产品艺术设计",
      "planCount": 9,
      "durationYears": 3,
      "tuitionPerYear": 7500,
      "campus": null,
      "remarks": "3年，7500元/年，不招色盲、色弱考生",
      "pdfPage": 655,
      "bookPage": 607
    },
    {
      "batchName": "高职高专普通批",
      "schoolCode": "14067",
      "schoolName": "柳州城市职业学院",
      "schoolTotalPlan": 1107,
      "schoolLocation": "广西壮族自治区柳州市",
      "consultPhone": "0772-5331029",
      "majorGroupCode": "151",
      "majorGroupPlan": 1107,
      "firstSubject": "物理",
      "secondSubject": "不限",
      "majorCode": "086",
      "majorName": "广告艺术设计",
      "planCount": 7,
      "durationYears": 3,
      "tuitionPerYear": 7500,
      "campus": null,
      "remarks": "3年，7500元/年，不招色盲、色弱考生",
      "pdfPage": 655,
      "bookPage": 607
    },
    {
      "batchName": "高职高专普通批",
      "schoolCode": "14067",
      "schoolName": "柳州城市职业学院",
      "schoolTotalPlan": 1107,
      "schoolLocation": "广西壮族自治区柳州市",
      "consultPhone": "0772-5331029",
      "majorGroupCode": "151",
      "majorGroupPlan": 1107,
      "firstSubject": "物理",
      "secondSubject": "不限",
      "majorCode": "087",
      "majorName": "人物形象设计",
      "planCount": 7,
      "durationYears": 3,
      "tuitionPerYear": 6500,
      "campus": null,
      "remarks": "3年，6500元/年，不招色盲、色弱考生",
      "pdfPage": 655,
      "bookPage": 607
    },
    {
      "batchName": "高职高专普通批",
      "schoolCode": "14067",
      "schoolName": "柳州城市职业学院",
      "schoolTotalPlan": 1107,
      "schoolLocation": "广西壮族自治区柳州市",
      "consultPhone": "0772-5331029",
      "majorGroupCode": "151",
      "majorGroupPlan": 1107,
      "firstSubject": "物理",
      "secondSubject": "不限",
      "majorCode": "088",
      "majorName": "影视多媒体技术",
      "planCount": 20,
      "durationYears": 3,
      "tuitionPerYear": 7500,
      "campus": null,
      "remarks": "3 年，7500 元/年，不招色盲、色弱考生",
      "pdfPage": 655,
      "bookPage": 607
    },
    {
      "batchName": "高职高专普通批",
      "schoolCode": "14067",
      "schoolName": "柳州城市职业学院",
      "schoolTotalPlan": 1107,
      "schoolLocation": "广西壮族自治区柳州市",
      "consultPhone": "0772-5331029",
      "majorGroupCode": "151",
      "majorGroupPlan": 1107,
      "firstSubject": "物理",
      "secondSubject": "不限",
      "majorCode": "089",
      "majorName": "学前教育",
      "planCount": 20,
      "durationYears": 3,
      "tuitionPerYear": 6000,
      "campus": null,
      "remarks": "3年,6000元/年",
      "pdfPage": 655,
      "bookPage": 607
    },
    {
      "batchName": "高职高专普通批",
      "schoolCode": "14067",
      "schoolName": "柳州城市职业学院",
      "schoolTotalPlan": 1107,
      "schoolLocation": "广西壮族自治区柳州市",
      "consultPhone": "0772-5331029",
      "majorGroupCode": "151",
      "majorGroupPlan": 1107,
      "firstSubject": "物理",
      "secondSubject": "不限",
      "majorCode": "090",
      "majorName": "小学教育",
      "planCount": 40,
      "durationYears": 3,
      "tuitionPerYear": 7000,
      "campus": null,
      "remarks": "3 年,7000 元/年",
      "pdfPage": 655,
      "bookPage": 607
    },
    {
      "batchName": "高职高专普通批",
      "schoolCode": "14067",
      "schoolName": "柳州城市职业学院",
      "schoolTotalPlan": 1107,
      "schoolLocation": "广西壮族自治区柳州市",
      "consultPhone": "0772-5331029",
      "majorGroupCode": "151",
      "majorGroupPlan": 1107,
      "firstSubject": "物理",
      "secondSubject": "不限",
      "majorCode": "091",
      "majorName": "现代家政服务与管理",
      "planCount": 17,
      "durationYears": 3,
      "tuitionPerYear": 6500,
      "campus": null,
      "remarks": "3 年，6500 元/年",
      "pdfPage": 655,
      "bookPage": 607
    },
    {
      "batchName": "高职高专普通批",
      "schoolCode": "14067",
      "schoolName": "柳州城市职业学院",
      "schoolTotalPlan": 1107,
      "schoolLocation": "广西壮族自治区柳州市",
      "consultPhone": "0772-5331029",
      "majorGroupCode": "151",
      "majorGroupPlan": 1107,
      "firstSubject": "物理",
      "secondSubject": "不限",
      "majorCode": "092",
      "majorName": "智慧健康养老服务与管理",
      "planCount": 22,
      "durationYears": 3,
      "tuitionPerYear": 7000,
      "campus": null,
      "remarks": "3 年,7000 元/年",
      "pdfPage": 655,
      "bookPage": 607
    }
  ]
}
