{
  "school": {
    "schoolCode": "14427",
    "schoolName": "广东信息工程职业学院",
    "schoolTotalPlan": 4,
    "schoolLocation": "广东省肇庆市",
    "consultPhone": "0758-3630618",
    "programCount": 4
  },
  "programs": [
    {
      "batchName": "高职高专普通批",
      "schoolCode": "14427",
      "schoolName": "广东信息工程职业学院",
      "schoolTotalPlan": 4,
      "schoolLocation": "广东省肇庆市",
      "consultPhone": "0758-3630618",
      "majorGroupCode": "102",
      "majorGroupPlan": 4,
      "firstSubject": "物理",
      "secondSubject": "不限",
      "majorCode": "005",
      "majorName": "物联网应用技术(华为鸿蒙创新班)",
      "planCount": 1,
      "durationYears": 3,
      "tuitionPerYear": 19300,
      "campus": null,
      "remarks": "3年,19300元/年",
      "pdfPage": 676,
      "bookPage": 628
    },
    {
      "batchName": "高职高专普通批",
      "schoolCode": "14427",
      "schoolName": "广东信息工程职业学院",
      "schoolTotalPlan": 4,
      "schoolLocation": "广东省肇庆市",
      "consultPhone": "0758-3630618",
      "majorGroupCode": "102",
      "majorGroupPlan": 4,
      "firstSubject": "物理",
      "secondSubject": "不限",
      "majorCode": "006",
      "majorName": "云计算技术应用(华为云计算创新班)",
      "planCount": 1,
      "durationYears": 3,
      "tuitionPerYear": 19300,
      "campus": null,
      "remarks": "3年,19300元/年",
      "pdfPage": 676,
      "bookPage": 628
    },
    {
      "batchName": "高职高专普通批",
      "schoolCode": "14427",
      "schoolName": "广东信息工程职业学院",
      "schoolTotalPlan": 4,
      "schoolLocation": "广东省肇庆市",
      "consultPhone": "0758-3630618",
      "majorGroupCode": "102",
      "majorGroupPlan": 4,
      "firstSubject": "物理",
      "secondSubject": "不限",
      "majorCode": "007",
      "majorName": "护理",
      "planCount": 1,
      "durationYears": 3,
      "tuitionPerYear": 17380,
      "campus": null,
      "remarks": "3 年,17380 元/年",
      "pdfPage": 676,
      "bookPage": 628
    },
    {
      "batchName": "高职高专普通批",
      "schoolCode": "14427",
      "schoolName": "广东信息工程职业学院",
      "schoolTotalPlan": 4,
      "schoolLocation": "广东省肇庆市",
      "consultPhone": "0758-3630618",
      "majorGroupCode": "102",
      "majorGroupPlan": 4,
      "firstSubject": "物理",
      "secondSubject": "不限",
      "majorCode": "008",
      "majorName": "口腔医学技术(德标产业学院)",
      "planCount": 1,
      "durationYears": 3,
      "tuitionPerYear": 23380,
      "campus": null,
      "remarks": "3年,23380元/年",
      "pdfPage": 676,
      "bookPage": 628
    }
  ]
}
